scons_tool_swigpy-0.1.2-py3.6-nspkg.pth
sconstool/swigpy/__init__.py
sconstool/swigpy/about.py
sconstool/swigpy/pyconf.py
scons_tool_swigpy-0.1.2.dist-info/METADATA
scons_tool_swigpy-0.1.2.dist-info/WHEEL
scons_tool_swigpy-0.1.2.dist-info/namespace_packages.txt
scons_tool_swigpy-0.1.2.dist-info/top_level.txt
scons_tool_swigpy-0.1.2.dist-info/RECORD
