Metadata-Version: 2.1
Name: scons-tool-swigpy
Version: 0.1.2
Summary: SCons tool to generate Python modules using SWIG
Home-page: https://github.com/ptomulik/scons-tool-swigpy
Author: Paweł Tomulik
Author-email: ptomulik@meil.pw.edu.pl
License: UNKNOWN
Platform: UNKNOWN
Requires-Python: >=2.7
Requires-Dist: scons-tool-util (>=0.1.9)
